{
  "activity_name": "younow.live/younow.live.ui.OnBoardingActivity", 
  "activity": {
    "root": {
      "scrollable-horizontal": false, 
      "draw": true, 
      "ancestors": [
        "android.widget.FrameLayout", 
        "android.view.ViewGroup", 
        "android.view.View", 
        "java.lang.Object"
      ], 
      "clickable": false, 
      "pressed": "not_pressed", 
      "focusable": false, 
      "long-clickable": false, 
      "enabled": true, 
      "bounds": [
        0, 
        0, 
        1440, 
        2560
      ], 
      "visibility": "visible", 
      "content-desc": [
        null
      ], 
      "rel-bounds": [
        0, 
        0, 
        1440, 
        2560
      ], 
      "focused": false, 
      "selected": false, 
      "scrollable-vertical": false, 
      "children": [
        {
          "scrollable-horizontal": false, 
          "draw": true, 
          "ancestors": [
            "android.view.ViewGroup", 
            "android.view.View", 
            "java.lang.Object"
          ], 
          "clickable": false, 
          "pressed": "not_pressed", 
          "focusable": false, 
          "long-clickable": false, 
          "enabled": true, 
          "bounds": [
            0, 
            0, 
            1440, 
            2392
          ], 
          "visibility": "visible", 
          "content-desc": [
            null
          ], 
          "rel-bounds": [
            0, 
            0, 
            1440, 
            2392
          ], 
          "focused": false, 
          "selected": false, 
          "scrollable-vertical": false, 
          "children": [
            {
              "resource-id": "android:id/action_mode_bar_stub", 
              "adapter-view": false, 
              "pointer": "ee02a06", 
              "scrollable-horizontal": false, 
              "ancestors": [
                "android.view.View", 
                "java.lang.Object"
              ], 
              "selected": false, 
              "content-desc": [
                null
              ], 
              "rel-bounds": [
                0, 
                0, 
                0, 
                0
              ], 
              "draw": true, 
              "focusable": false, 
              "long-clickable": false, 
              "visibility": "gone", 
              "focused": false, 
              "clickable": false, 
              "abs-pos": true, 
              "class": "android.view.ViewStub", 
              "visible-to-user": false, 
              "package": "android", 
              "enabled": true, 
              "bounds": [
                0, 
                0, 
                0, 
                0
              ], 
              "pressed": "not_pressed", 
              "scrollable-vertical": false
            }, 
            {
              "scrollable-horizontal": false, 
              "draw": true, 
              "ancestors": [
                "android.view.ViewGroup", 
                "android.view.View", 
                "java.lang.Object"
              ], 
              "clickable": false, 
              "pressed": "not_pressed", 
              "focusable": false, 
              "long-clickable": false, 
              "enabled": true, 
              "bounds": [
                0, 
                0, 
                1440, 
                2392
              ], 
              "visibility": "visible", 
              "content-desc": [
                null
              ], 
              "rel-bounds": [
                0, 
                0, 
                1440, 
                2392
              ], 
              "focused": false, 
              "selected": false, 
              "scrollable-vertical": false, 
              "children": [
                {
                  "resource-id": "younow.live:id/action_bar_root", 
                  "adapter-view": false, 
                  "pointer": "ae0eef4", 
                  "children": [
                    {
                      "resource-id": "younow.live:id/action_mode_bar_stub", 
                      "adapter-view": false, 
                      "pointer": "f4c461d", 
                      "scrollable-horizontal": false, 
                      "ancestors": [
                        "android.view.View", 
                        "java.lang.Object"
                      ], 
                      "selected": false, 
                      "content-desc": [
                        null
                      ], 
                      "rel-bounds": [
                        0, 
                        0, 
                        0, 
                        0
                      ], 
                      "draw": true, 
                      "focusable": false, 
                      "long-clickable": false, 
                      "visibility": "gone", 
                      "focused": false, 
                      "clickable": false, 
                      "abs-pos": true, 
                      "class": "android.support.v7.widget.ViewStubCompat", 
                      "visible-to-user": false, 
                      "package": "younow.live", 
                      "enabled": true, 
                      "bounds": [
                        0, 
                        0, 
                        0, 
                        0
                      ], 
                      "pressed": "not_pressed", 
                      "scrollable-vertical": false
                    }, 
                    {
                      "resource-id": "android:id/content", 
                      "adapter-view": false, 
                      "pointer": "844e092", 
                      "children": [
                        {
                          "resource-id": "younow.live:id/onboarding_layout", 
                          "adapter-view": false, 
                          "pointer": "4ac4a63", 
                          "children": [
                            {
                              "resource-id": "younow.live:id/fragment_main", 
                              "adapter-view": false, 
                              "pointer": "7980660", 
                              "children": [
                                {
                                  "scrollable-horizontal": false, 
                                  "draw": true, 
                                  "ancestors": [
                                    "android.view.ViewGroup", 
                                    "android.view.View", 
                                    "java.lang.Object"
                                  ], 
                                  "clickable": false, 
                                  "pressed": "not_pressed", 
                                  "focusable": false, 
                                  "long-clickable": false, 
                                  "enabled": true, 
                                  "bounds": [
                                    0, 
                                    0, 
                                    1440, 
                                    2392
                                  ], 
                                  "visibility": "visible", 
                                  "content-desc": [
                                    null
                                  ], 
                                  "rel-bounds": [
                                    0, 
                                    0, 
                                    1440, 
                                    2392
                                  ], 
                                  "focused": false, 
                                  "selected": false, 
                                  "scrollable-vertical": false, 
                                  "children": [
                                    {
                                      "resource-id": "younow.live:id/video_holder", 
                                      "adapter-view": false, 
                                      "pointer": "dcc73de", 
                                      "children": [
                                        {
                                          "resource-id": "younow.live:id/login_bg_video", 
                                          "adapter-view": false, 
                                          "pointer": "70f29bf", 
                                          "scrollable-horizontal": false, 
                                          "ancestors": [
                                            "android.view.SurfaceView", 
                                            "android.view.View", 
                                            "java.lang.Object"
                                          ], 
                                          "selected": false, 
                                          "content-desc": [
                                            null
                                          ], 
                                          "rel-bounds": [
                                            0, 
                                            0, 
                                            1440, 
                                            2392
                                          ], 
                                          "draw": true, 
                                          "focusable": true, 
                                          "long-clickable": false, 
                                          "visibility": "visible", 
                                          "focused": true, 
                                          "clickable": false, 
                                          "abs-pos": true, 
                                          "class": "android.widget.VideoView", 
                                          "visible-to-user": true, 
                                          "package": "younow.live", 
                                          "enabled": true, 
                                          "bounds": [
                                            0, 
                                            0, 
                                            1440, 
                                            2392
                                          ], 
                                          "pressed": "not_pressed", 
                                          "scrollable-vertical": false
                                        }
                                      ], 
                                      "scrollable-horizontal": false, 
                                      "ancestors": [
                                        "android.view.ViewGroup", 
                                        "android.view.View", 
                                        "java.lang.Object"
                                      ], 
                                      "selected": false, 
                                      "content-desc": [
                                        null
                                      ], 
                                      "rel-bounds": [
                                        0, 
                                        0, 
                                        1440, 
                                        2392
                                      ], 
                                      "draw": true, 
                                      "focusable": false, 
                                      "long-clickable": false, 
                                      "visibility": "visible", 
                                      "focused": false, 
                                      "clickable": false, 
                                      "abs-pos": true, 
                                      "class": "android.widget.RelativeLayout", 
                                      "visible-to-user": true, 
                                      "package": "younow.live", 
                                      "enabled": true, 
                                      "bounds": [
                                        0, 
                                        0, 
                                        1440, 
                                        2392
                                      ], 
                                      "pressed": "not_pressed", 
                                      "scrollable-vertical": false
                                    }, 
                                    {
                                      "resource-id": "younow.live:id/login_main_content_container", 
                                      "adapter-view": false, 
                                      "pointer": "8e7288c", 
                                      "children": [
                                        {
                                          "text": "\u00d1", 
                                          "resource-id": "younow.live:id/experiment_login_icon_testd", 
                                          "adapter-view": false, 
                                          "pointer": "10f1bd5", 
                                          "scrollable-horizontal": false, 
                                          "ancestors": [
                                            "android.support.v7.widget.AppCompatTextView", 
                                            "android.widget.TextView", 
                                            "android.view.View", 
                                            "java.lang.Object"
                                          ], 
                                          "selected": false, 
                                          "content-desc": [
                                            null
                                          ], 
                                          "rel-bounds": [
                                            401, 
                                            84, 
                                            1038, 
                                            568
                                          ], 
                                          "draw": false, 
                                          "focusable": false, 
                                          "long-clickable": false, 
                                          "visibility": "visible", 
                                          "focused": false, 
                                          "clickable": false, 
                                          "abs-pos": true, 
                                          "font-family": "default", 
                                          "class": "younow.live.ui.views.YouNowFontIconView", 
                                          "visible-to-user": true, 
                                          "package": "younow.live", 
                                          "enabled": true, 
                                          "bounds": [
                                            401, 
                                            333, 
                                            1038, 
                                            817
                                          ], 
                                          "pressed": "not_pressed", 
                                          "scrollable-vertical": false
                                        }, 
                                        {
                                          "text": "Live Stream Video Chat", 
                                          "resource-id": "younow.live:id/login_slogan", 
                                          "adapter-view": false, 
                                          "pointer": "9a7efea", 
                                          "scrollable-horizontal": false, 
                                          "ancestors": [
                                            "android.widget.TextView", 
                                            "android.view.View", 
                                            "java.lang.Object"
                                          ], 
                                          "selected": false, 
                                          "content-desc": [
                                            null
                                          ], 
                                          "rel-bounds": [
                                            185, 
                                            534, 
                                            1255, 
                                            674
                                          ], 
                                          "draw": false, 
                                          "focusable": false, 
                                          "long-clickable": false, 
                                          "visibility": "visible", 
                                          "focused": false, 
                                          "clickable": false, 
                                          "abs-pos": true, 
                                          "font-family": "sans-serif-light", 
                                          "class": "android.support.v7.widget.AppCompatTextView", 
                                          "visible-to-user": true, 
                                          "package": "younow.live", 
                                          "enabled": true, 
                                          "bounds": [
                                            185, 
                                            783, 
                                            1255, 
                                            923
                                          ], 
                                          "pressed": "not_pressed", 
                                          "scrollable-vertical": false
                                        }, 
                                        {
                                          "scrollable-horizontal": false, 
                                          "draw": true, 
                                          "ancestors": [
                                            "android.view.ViewGroup", 
                                            "android.view.View", 
                                            "java.lang.Object"
                                          ], 
                                          "clickable": false, 
                                          "pressed": "not_pressed", 
                                          "focusable": false, 
                                          "long-clickable": false, 
                                          "enabled": true, 
                                          "bounds": [
                                            230, 
                                            1028, 
                                            1210, 
                                            1186
                                          ], 
                                          "visibility": "visible", 
                                          "content-desc": [
                                            null
                                          ], 
                                          "rel-bounds": [
                                            230, 
                                            779, 
                                            1210, 
                                            937
                                          ], 
                                          "focused": false, 
                                          "selected": false, 
                                          "scrollable-vertical": false, 
                                          "children": [
                                            {
                                              "text": "", 
                                              "resource-id": "younow.live:id/facebook_login_button", 
                                              "adapter-view": false, 
                                              "pointer": "6244178", 
                                              "scrollable-horizontal": false, 
                                              "ancestors": [
                                                "com.facebook.login.widget.LoginButton", 
                                                "com.facebook.FacebookButtonBase", 
                                                "android.widget.Button", 
                                                "android.widget.TextView", 
                                                "android.view.View", 
                                                "java.lang.Object"
                                              ], 
                                              "selected": false, 
                                              "content-desc": [
                                                null
                                              ], 
                                              "rel-bounds": [
                                                0, 
                                                0, 
                                                980, 
                                                158
                                              ], 
                                              "draw": false, 
                                              "focusable": false, 
                                              "long-clickable": false, 
                                              "visibility": "visible", 
                                              "focused": false, 
                                              "clickable": true, 
                                              "abs-pos": true, 
                                              "class": "younow.live.ui.views.YouNowFacebookButton", 
                                              "visible-to-user": true, 
                                              "package": "younow.live", 
                                              "enabled": true, 
                                              "bounds": [
                                                230, 
                                                1028, 
                                                1210, 
                                                1186
                                              ], 
                                              "pressed": "not_pressed", 
                                              "scrollable-vertical": false
                                            }, 
                                            {
                                              "text": "h", 
                                              "resource-id": "younow.live:id/facebook_login_button_font_icon", 
                                              "adapter-view": false, 
                                              "pointer": "432a051", 
                                              "scrollable-horizontal": false, 
                                              "ancestors": [
                                                "younow.live.ui.views.YouNowFontIconView", 
                                                "android.support.v7.widget.AppCompatTextView", 
                                                "android.widget.TextView", 
                                                "android.view.View", 
                                                "java.lang.Object"
                                              ], 
                                              "selected": false, 
                                              "content-desc": [
                                                null
                                              ], 
                                              "rel-bounds": [
                                                35, 
                                                0, 
                                                142, 
                                                158
                                              ], 
                                              "draw": false, 
                                              "focusable": false, 
                                              "long-clickable": false, 
                                              "visibility": "visible", 
                                              "focused": false, 
                                              "clickable": false, 
                                              "abs-pos": true, 
                                              "font-family": "default", 
                                              "class": "younow.live.ui.views.YouNowTwitterButton", 
                                              "visible-to-user": true, 
                                              "package": "younow.live", 
                                              "enabled": true, 
                                              "bounds": [
                                                265, 
                                                1028, 
                                                372, 
                                                1186
                                              ], 
                                              "pressed": "not_pressed", 
                                              "scrollable-vertical": false
                                            }, 
                                            {
                                              "text": "Facebook", 
                                              "scrollable-vertical": false, 
                                              "adapter-view": false, 
                                              "pointer": "60d20b6", 
                                              "scrollable-horizontal": false, 
                                              "ancestors": [
                                                "android.widget.TextView", 
                                                "android.view.View", 
                                                "java.lang.Object"
                                              ], 
                                              "selected": false, 
                                              "content-desc": [
                                                null
                                              ], 
                                              "rel-bounds": [
                                                350, 
                                                36, 
                                                629, 
                                                122
                                              ], 
                                              "draw": false, 
                                              "focusable": false, 
                                              "long-clickable": false, 
                                              "visibility": "visible", 
                                              "focused": false, 
                                              "clickable": false, 
                                              "abs-pos": true, 
                                              "font-family": "sans-serif", 
                                              "class": "android.support.v7.widget.AppCompatTextView", 
                                              "visible-to-user": true, 
                                              "enabled": true, 
                                              "bounds": [
                                                580, 
                                                1064, 
                                                859, 
                                                1150
                                              ], 
                                              "pressed": "not_pressed"
                                            }
                                          ], 
                                          "adapter-view": false, 
                                          "abs-pos": true, 
                                          "pointer": "96a2db", 
                                          "class": "android.widget.RelativeLayout", 
                                          "visible-to-user": true
                                        }, 
                                        {
                                          "resource-id": "younow.live:id/twitter_login_button_layout", 
                                          "adapter-view": false, 
                                          "pointer": "65291b7", 
                                          "children": [
                                            {
                                              "text": "i", 
                                              "resource-id": "younow.live:id/twitter_login_button", 
                                              "adapter-view": false, 
                                              "pointer": "417fd24", 
                                              "scrollable-horizontal": false, 
                                              "ancestors": [
                                                "younow.live.ui.views.YouNowFontIconView", 
                                                "android.support.v7.widget.AppCompatTextView", 
                                                "android.widget.TextView", 
                                                "android.view.View", 
                                                "java.lang.Object"
                                              ], 
                                              "selected": false, 
                                              "content-desc": [
                                                null
                                              ], 
                                              "rel-bounds": [
                                                35, 
                                                0, 
                                                142, 
                                                158
                                              ], 
                                              "draw": false, 
                                              "focusable": false, 
                                              "long-clickable": false, 
                                              "visibility": "visible", 
                                              "focused": false, 
                                              "clickable": false, 
                                              "abs-pos": true, 
                                              "font-family": "default", 
                                              "class": "younow.live.ui.views.YouNowTwitterButton", 
                                              "visible-to-user": true, 
                                              "package": "younow.live", 
                                              "enabled": true, 
                                              "bounds": [
                                                265, 
                                                1242, 
                                                372, 
                                                1400
                                              ], 
                                              "pressed": "not_pressed", 
                                              "scrollable-vertical": false
                                            }, 
                                            {
                                              "text": "Twitter", 
                                              "scrollable-vertical": false, 
                                              "adapter-view": false, 
                                              "pointer": "b2ff08d", 
                                              "scrollable-horizontal": false, 
                                              "ancestors": [
                                                "android.widget.TextView", 
                                                "android.view.View", 
                                                "java.lang.Object"
                                              ], 
                                              "selected": false, 
                                              "content-desc": [
                                                null
                                              ], 
                                              "rel-bounds": [
                                                391, 
                                                36, 
                                                589, 
                                                122
                                              ], 
                                              "draw": false, 
                                              "focusable": false, 
                                              "long-clickable": false, 
                                              "visibility": "visible", 
                                              "focused": false, 
                                              "clickable": false, 
                                              "abs-pos": true, 
                                              "font-family": "sans-serif", 
                                              "class": "android.support.v7.widget.AppCompatTextView", 
                                              "visible-to-user": true, 
                                              "enabled": true, 
                                              "bounds": [
                                                621, 
                                                1278, 
                                                819, 
                                                1364
                                              ], 
                                              "pressed": "not_pressed"
                                            }
                                          ], 
                                          "scrollable-horizontal": false, 
                                          "ancestors": [
                                            "android.view.ViewGroup", 
                                            "android.view.View", 
                                            "java.lang.Object"
                                          ], 
                                          "selected": false, 
                                          "content-desc": [
                                            null
                                          ], 
                                          "rel-bounds": [
                                            230, 
                                            993, 
                                            1210, 
                                            1151
                                          ], 
                                          "draw": true, 
                                          "focusable": false, 
                                          "long-clickable": false, 
                                          "visibility": "visible", 
                                          "focused": false, 
                                          "clickable": true, 
                                          "abs-pos": true, 
                                          "class": "android.widget.RelativeLayout", 
                                          "visible-to-user": true, 
                                          "package": "younow.live", 
                                          "enabled": true, 
                                          "bounds": [
                                            230, 
                                            1242, 
                                            1210, 
                                            1400
                                          ], 
                                          "pressed": "not_pressed", 
                                          "scrollable-vertical": false
                                        }, 
                                        {
                                          "resource-id": "younow.live:id/google_plus_login_button", 
                                          "adapter-view": false, 
                                          "pointer": "8c29242", 
                                          "children": [
                                            {
                                              "text": "f", 
                                              "resource-id": "younow.live:id/google_plus_login_button_font_icon", 
                                              "adapter-view": false, 
                                              "pointer": "4749253", 
                                              "scrollable-horizontal": false, 
                                              "ancestors": [
                                                "android.support.v7.widget.AppCompatTextView", 
                                                "android.widget.TextView", 
                                                "android.view.View", 
                                                "java.lang.Object"
                                              ], 
                                              "selected": false, 
                                              "content-desc": [
                                                null
                                              ], 
                                              "rel-bounds": [
                                                35, 
                                                38, 
                                                142, 
                                                120
                                              ], 
                                              "draw": false, 
                                              "focusable": false, 
                                              "long-clickable": false, 
                                              "visibility": "visible", 
                                              "focused": false, 
                                              "clickable": false, 
                                              "abs-pos": true, 
                                              "font-family": "default", 
                                              "class": "younow.live.ui.views.YouNowFontIconView", 
                                              "visible-to-user": true, 
                                              "package": "younow.live", 
                                              "enabled": true, 
                                              "bounds": [
                                                265, 
                                                1494, 
                                                372, 
                                                1576
                                              ], 
                                              "pressed": "not_pressed", 
                                              "scrollable-vertical": false
                                            }, 
                                            {
                                              "text": "Google", 
                                              "scrollable-vertical": false, 
                                              "adapter-view": false, 
                                              "pointer": "969c790", 
                                              "scrollable-horizontal": false, 
                                              "ancestors": [
                                                "android.widget.TextView", 
                                                "android.view.View", 
                                                "java.lang.Object"
                                              ], 
                                              "selected": false, 
                                              "content-desc": [
                                                null
                                              ], 
                                              "rel-bounds": [
                                                388, 
                                                36, 
                                                592, 
                                                122
                                              ], 
                                              "draw": false, 
                                              "focusable": false, 
                                              "long-clickable": false, 
                                              "visibility": "visible", 
                                              "focused": false, 
                                              "clickable": false, 
                                              "abs-pos": true, 
                                              "font-family": "sans-serif", 
                                              "class": "android.support.v7.widget.AppCompatTextView", 
                                              "visible-to-user": true, 
                                              "enabled": true, 
                                              "bounds": [
                                                618, 
                                                1492, 
                                                822, 
                                                1578
                                              ], 
                                              "pressed": "not_pressed"
                                            }
                                          ], 
                                          "scrollable-horizontal": false, 
                                          "ancestors": [
                                            "android.view.ViewGroup", 
                                            "android.view.View", 
                                            "java.lang.Object"
                                          ], 
                                          "selected": false, 
                                          "content-desc": [
                                            null
                                          ], 
                                          "rel-bounds": [
                                            230, 
                                            1207, 
                                            1210, 
                                            1365
                                          ], 
                                          "draw": true, 
                                          "focusable": false, 
                                          "long-clickable": false, 
                                          "visibility": "visible", 
                                          "focused": false, 
                                          "clickable": true, 
                                          "abs-pos": true, 
                                          "class": "android.widget.RelativeLayout", 
                                          "visible-to-user": true, 
                                          "package": "younow.live", 
                                          "enabled": true, 
                                          "bounds": [
                                            230, 
                                            1456, 
                                            1210, 
                                            1614
                                          ], 
                                          "pressed": "not_pressed", 
                                          "scrollable-vertical": false
                                        }, 
                                        {
                                          "text": "More Options", 
                                          "resource-id": "younow.live:id/more_options_button", 
                                          "adapter-view": false, 
                                          "pointer": "6380889", 
                                          "scrollable-horizontal": false, 
                                          "ancestors": [
                                            "android.widget.TextView", 
                                            "android.view.View", 
                                            "java.lang.Object"
                                          ], 
                                          "selected": false, 
                                          "content-desc": [
                                            null
                                          ], 
                                          "rel-bounds": [
                                            230, 
                                            1421, 
                                            1210, 
                                            1579
                                          ], 
                                          "draw": false, 
                                          "focusable": false, 
                                          "long-clickable": false, 
                                          "visibility": "visible", 
                                          "focused": false, 
                                          "clickable": true, 
                                          "abs-pos": true, 
                                          "font-family": "sans-serif", 
                                          "class": "android.support.v7.widget.AppCompatTextView", 
                                          "visible-to-user": true, 
                                          "package": "younow.live", 
                                          "enabled": true, 
                                          "bounds": [
                                            230, 
                                            1670, 
                                            1210, 
                                            1828
                                          ], 
                                          "pressed": "not_pressed", 
                                          "scrollable-vertical": false
                                        }, 
                                        {
                                          "resource-id": "younow.live:id/instagram_login_button", 
                                          "adapter-view": false, 
                                          "pointer": "b6b908e", 
                                          "children": [
                                            {
                                              "text": "j", 
                                              "resource-id": "younow.live:id/instagram_login_button_font_icon", 
                                              "adapter-view": false, 
                                              "pointer": "eac00af", 
                                              "scrollable-horizontal": false, 
                                              "ancestors": [
                                                "android.support.v7.widget.AppCompatTextView", 
                                                "android.widget.TextView", 
                                                "android.view.View", 
                                                "java.lang.Object"
                                              ], 
                                              "selected": false, 
                                              "content-desc": [
                                                null
                                              ], 
                                              "rel-bounds": [
                                                0, 
                                                0, 
                                                0, 
                                                0
                                              ], 
                                              "draw": false, 
                                              "focusable": false, 
                                              "long-clickable": false, 
                                              "visibility": "visible", 
                                              "focused": false, 
                                              "clickable": false, 
                                              "abs-pos": true, 
                                              "font-family": "default", 
                                              "class": "younow.live.ui.views.YouNowFontIconView", 
                                              "visible-to-user": false, 
                                              "package": "younow.live", 
                                              "enabled": true, 
                                              "bounds": [
                                                0, 
                                                249, 
                                                0, 
                                                249
                                              ], 
                                              "pressed": "not_pressed", 
                                              "scrollable-vertical": false
                                            }, 
                                            {
                                              "text": "Instagram", 
                                              "resource-id": "younow.live:id/instagram_login_button_textview", 
                                              "adapter-view": false, 
                                              "pointer": "dcbccbc", 
                                              "scrollable-horizontal": false, 
                                              "ancestors": [
                                                "android.widget.TextView", 
                                                "android.view.View", 
                                                "java.lang.Object"
                                              ], 
                                              "selected": false, 
                                              "content-desc": [
                                                null
                                              ], 
                                              "rel-bounds": [
                                                0, 
                                                0, 
                                                0, 
                                                0
                                              ], 
                                              "draw": false, 
                                              "focusable": false, 
                                              "long-clickable": false, 
                                              "visibility": "visible", 
                                              "focused": false, 
                                              "clickable": false, 
                                              "abs-pos": true, 
                                              "font-family": "sans-serif", 
                                              "class": "android.support.v7.widget.AppCompatTextView", 
                                              "visible-to-user": false, 
                                              "package": "younow.live", 
                                              "enabled": true, 
                                              "bounds": [
                                                0, 
                                                249, 
                                                0, 
                                                249
                                              ], 
                                              "pressed": "not_pressed", 
                                              "scrollable-vertical": false
                                            }
                                          ], 
                                          "scrollable-horizontal": false, 
                                          "ancestors": [
                                            "android.view.ViewGroup", 
                                            "android.view.View", 
                                            "java.lang.Object"
                                          ], 
                                          "selected": false, 
                                          "content-desc": [
                                            null
                                          ], 
                                          "rel-bounds": [
                                            0, 
                                            0, 
                                            0, 
                                            0
                                          ], 
                                          "draw": true, 
                                          "focusable": false, 
                                          "long-clickable": false, 
                                          "visibility": "gone", 
                                          "focused": false, 
                                          "clickable": true, 
                                          "abs-pos": true, 
                                          "class": "android.widget.LinearLayout", 
                                          "visible-to-user": false, 
                                          "package": "younow.live", 
                                          "enabled": true, 
                                          "bounds": [
                                            0, 
                                            249, 
                                            0, 
                                            249
                                          ], 
                                          "pressed": "not_pressed", 
                                          "scrollable-vertical": false
                                        }, 
                                        {
                                          "text": "By signing in you agree to our terms of use", 
                                          "resource-id": "younow.live:id/login_terms", 
                                          "adapter-view": false, 
                                          "pointer": "d8fa445", 
                                          "scrollable-horizontal": false, 
                                          "ancestors": [
                                            "android.widget.TextView", 
                                            "android.view.View", 
                                            "java.lang.Object"
                                          ], 
                                          "selected": false, 
                                          "content-desc": [
                                            null
                                          ], 
                                          "rel-bounds": [
                                            230, 
                                            1649, 
                                            1210, 
                                            1810
                                          ], 
                                          "draw": false, 
                                          "focusable": false, 
                                          "long-clickable": false, 
                                          "visibility": "visible", 
                                          "focused": false, 
                                          "clickable": true, 
                                          "abs-pos": true, 
                                          "font-family": "sans-serif-light", 
                                          "class": "android.support.v7.widget.AppCompatTextView", 
                                          "visible-to-user": true, 
                                          "package": "younow.live", 
                                          "enabled": true, 
                                          "bounds": [
                                            230, 
                                            1898, 
                                            1210, 
                                            2059
                                          ], 
                                          "pressed": "not_pressed", 
                                          "scrollable-vertical": false
                                        }
                                      ], 
                                      "scrollable-horizontal": false, 
                                      "ancestors": [
                                        "android.view.ViewGroup", 
                                        "android.view.View", 
                                        "java.lang.Object"
                                      ], 
                                      "selected": false, 
                                      "content-desc": [
                                        null
                                      ], 
                                      "rel-bounds": [
                                        0, 
                                        249, 
                                        1440, 
                                        2143
                                      ], 
                                      "draw": true, 
                                      "focusable": false, 
                                      "long-clickable": false, 
                                      "visibility": "visible", 
                                      "focused": false, 
                                      "clickable": false, 
                                      "abs-pos": true, 
                                      "class": "android.widget.LinearLayout", 
                                      "visible-to-user": true, 
                                      "package": "younow.live", 
                                      "enabled": true, 
                                      "bounds": [
                                        0, 
                                        249, 
                                        1440, 
                                        2143
                                      ], 
                                      "pressed": "not_pressed", 
                                      "scrollable-vertical": false
                                    }
                                  ], 
                                  "adapter-view": false, 
                                  "abs-pos": true, 
                                  "pointer": "bec2719", 
                                  "class": "android.widget.RelativeLayout", 
                                  "visible-to-user": true
                                }
                              ], 
                              "scrollable-horizontal": false, 
                              "ancestors": [
                                "android.view.ViewGroup", 
                                "android.view.View", 
                                "java.lang.Object"
                              ], 
                              "selected": false, 
                              "content-desc": [
                                null
                              ], 
                              "rel-bounds": [
                                0, 
                                0, 
                                1440, 
                                2392
                              ], 
                              "draw": true, 
                              "focusable": false, 
                              "long-clickable": false, 
                              "visibility": "visible", 
                              "focused": false, 
                              "clickable": false, 
                              "abs-pos": true, 
                              "class": "android.widget.FrameLayout", 
                              "visible-to-user": true, 
                              "package": "younow.live", 
                              "enabled": true, 
                              "bounds": [
                                0, 
                                0, 
                                1440, 
                                2392
                              ], 
                              "pressed": "not_pressed", 
                              "scrollable-vertical": false
                            }
                          ], 
                          "scrollable-horizontal": false, 
                          "ancestors": [
                            "android.view.ViewGroup", 
                            "android.view.View", 
                            "java.lang.Object"
                          ], 
                          "selected": false, 
                          "content-desc": [
                            null
                          ], 
                          "rel-bounds": [
                            0, 
                            0, 
                            1440, 
                            2392
                          ], 
                          "draw": true, 
                          "focusable": false, 
                          "long-clickable": false, 
                          "visibility": "visible", 
                          "focused": false, 
                          "clickable": false, 
                          "abs-pos": true, 
                          "class": "android.widget.FrameLayout", 
                          "visible-to-user": true, 
                          "package": "younow.live", 
                          "enabled": true, 
                          "bounds": [
                            0, 
                            0, 
                            1440, 
                            2392
                          ], 
                          "pressed": "not_pressed", 
                          "scrollable-vertical": false
                        }
                      ], 
                      "scrollable-horizontal": false, 
                      "ancestors": [
                        "android.widget.FrameLayout", 
                        "android.view.ViewGroup", 
                        "android.view.View", 
                        "java.lang.Object"
                      ], 
                      "selected": false, 
                      "content-desc": [
                        null
                      ], 
                      "rel-bounds": [
                        0, 
                        0, 
                        1440, 
                        2392
                      ], 
                      "draw": true, 
                      "focusable": false, 
                      "long-clickable": false, 
                      "visibility": "visible", 
                      "focused": false, 
                      "clickable": false, 
                      "abs-pos": true, 
                      "class": "android.support.v7.widget.ContentFrameLayout", 
                      "visible-to-user": true, 
                      "package": "android", 
                      "enabled": true, 
                      "bounds": [
                        0, 
                        0, 
                        1440, 
                        2392
                      ], 
                      "pressed": "not_pressed", 
                      "scrollable-vertical": false
                    }
                  ], 
                  "scrollable-horizontal": false, 
                  "ancestors": [
                    "android.widget.LinearLayout", 
                    "android.view.ViewGroup", 
                    "android.view.View", 
                    "java.lang.Object"
                  ], 
                  "selected": false, 
                  "content-desc": [
                    null
                  ], 
                  "rel-bounds": [
                    0, 
                    0, 
                    1440, 
                    2392
                  ], 
                  "draw": true, 
                  "focusable": false, 
                  "long-clickable": false, 
                  "visibility": "visible", 
                  "focused": false, 
                  "clickable": false, 
                  "abs-pos": true, 
                  "class": "android.support.v7.widget.FitWindowsLinearLayout", 
                  "visible-to-user": true, 
                  "package": "younow.live", 
                  "enabled": true, 
                  "bounds": [
                    0, 
                    0, 
                    1440, 
                    2392
                  ], 
                  "pressed": "not_pressed", 
                  "scrollable-vertical": false
                }
              ], 
              "adapter-view": false, 
              "abs-pos": true, 
              "pointer": "8e3e8c7", 
              "class": "android.widget.FrameLayout", 
              "visible-to-user": true
            }
          ], 
          "adapter-view": false, 
          "abs-pos": true, 
          "pointer": "3d1bce1", 
          "class": "android.widget.LinearLayout", 
          "visible-to-user": true
        }, 
        {
          "resource-id": "android:id/navigationBarBackground", 
          "adapter-view": false, 
          "pointer": "c94279a", 
          "scrollable-horizontal": false, 
          "ancestors": [
            "java.lang.Object"
          ], 
          "selected": false, 
          "content-desc": [
            null
          ], 
          "rel-bounds": [
            0, 
            2392, 
            1440, 
            2560
          ], 
          "draw": false, 
          "focusable": false, 
          "long-clickable": false, 
          "visibility": "visible", 
          "focused": false, 
          "clickable": false, 
          "abs-pos": true, 
          "class": "android.view.View", 
          "visible-to-user": true, 
          "package": "android", 
          "enabled": true, 
          "bounds": [
            0, 
            2392, 
            1440, 
            2560
          ], 
          "pressed": "not_pressed", 
          "scrollable-vertical": false
        }
      ], 
      "adapter-view": false, 
      "abs-pos": true, 
      "pointer": "332b648", 
      "class": "com.android.internal.policy.PhoneWindow$DecorView", 
      "visible-to-user": true
    }, 
    "added_fragments": [], 
    "active_fragments": []
  }, 
  "is_keyboard_deployed": false, 
  "request_id": "399"
}